excel_toolkit/__init__.py
excel_toolkit/__main__.py
excel_toolkit/cli.py
excel_toolkit/commands/__init__.py
excel_toolkit/commands/aggregate.py
excel_toolkit/commands/append.py
excel_toolkit/commands/clean.py
excel_toolkit/commands/common.py
excel_toolkit/commands/compare.py
excel_toolkit/commands/convert.py
excel_toolkit/commands/count.py
excel_toolkit/commands/dedupe.py
excel_toolkit/commands/export.py
excel_toolkit/commands/fill.py
excel_toolkit/commands/filter.py
excel_toolkit/commands/group.py
excel_toolkit/commands/head.py
excel_toolkit/commands/info.py
excel_toolkit/commands/join.py
excel_toolkit/commands/merge.py
excel_toolkit/commands/pivot.py
excel_toolkit/commands/rename.py
excel_toolkit/commands/search.py
excel_toolkit/commands/select.py
excel_toolkit/commands/sort.py
excel_toolkit/commands/stats.py
excel_toolkit/commands/strip.py
excel_toolkit/commands/tail.py
excel_toolkit/commands/transform.py
excel_toolkit/commands/unique.py
excel_toolkit/commands/validate.py
excel_toolkit/core/__init__.py
excel_toolkit/core/const.py
excel_toolkit/core/exceptions.py
excel_toolkit/core/file_handlers.py
excel_toolkit/fp/__init__.py
excel_toolkit/fp/_maybe.py
excel_toolkit/fp/_result.py
excel_toolkit/fp/immutable.py
excel_toolkit/fp/maybe.py
excel_toolkit/fp/result.py
excel_toolkit/models/__init__.py
excel_toolkit/models/error_types.py
excel_toolkit/operations/__init__.py
excel_toolkit/operations/aggregating.py
excel_toolkit/operations/cleaning.py
excel_toolkit/operations/comparing.py
excel_toolkit/operations/filtering.py
excel_toolkit/operations/joining.py
excel_toolkit/operations/pivoting.py
excel_toolkit/operations/sorting.py
excel_toolkit/operations/transforming.py
excel_toolkit/operations/validation.py
excel_toolkit/templates/__init__.py
excel_toolkit/utils/__init__.py
excel_toolkit_cwd-0.3.0.dist-info/METADATA
excel_toolkit_cwd-0.3.0.dist-info/WHEEL
excel_toolkit_cwd-0.3.0.dist-info/entry_points.txt
excel_toolkit_cwd-0.3.0.dist-info/licenses/LICENSE
excel_toolkit_cwd-0.3.0.dist-info/RECORD
