Metadata-Version: 2.4
Name: excel-toolkit-cwd
Version: 0.3.0
Summary: Command-line toolkit for Excel data manipulation and analysis
Project-URL: Homepage, https://github.com/AliiiBenn/excel-toolkit
Project-URL: Repository, https://github.com/AliiiBenn/excel-toolkit
Project-URL: Documentation, https://github.com/AliiiBenn/excel-toolkit/blob/main/README.md
Project-URL: Bug Tracker, https://github.com/AliiiBenn/excel-toolkit/issues
Author: Excel Toolkit Contributors
License: MIT
License-File: LICENSE
Keywords: cli,csv,data,etl,excel,pandas,spreadsheet
Classifier: Development Status :: 4 - Beta
Classifier: Environment :: Console
Classifier: Intended Audience :: Developers
Classifier: Intended Audience :: End Users/Desktop
Classifier: Intended Audience :: System Administrators
Classifier: License :: OSI Approved :: MIT License
Classifier: Operating System :: OS Independent
Classifier: Programming Language :: Python :: 3
Classifier: Programming Language :: Python :: 3.10
Classifier: Programming Language :: Python :: 3.11
Classifier: Programming Language :: Python :: 3.12
Classifier: Programming Language :: Python :: 3.13
Classifier: Programming Language :: Python :: 3.14
Classifier: Topic :: Office/Business :: Financial :: Spreadsheet
Classifier: Topic :: Scientific/Engineering :: Information Analysis
Classifier: Topic :: Utilities
Requires-Python: >=3.10
Requires-Dist: openpyxl>=3.1.0
Requires-Dist: pandas>=2.0.0
Requires-Dist: tabulate>=0.9.0
Requires-Dist: typer>=0.9.0
Provides-Extra: dev
Requires-Dist: hypothesis>=6.0.0; extra == 'dev'
Requires-Dist: mypy>=1.0.0; extra == 'dev'
Requires-Dist: pytest-cov>=4.0.0; extra == 'dev'
Requires-Dist: pytest>=7.0.0; extra == 'dev'
Requires-Dist: ruff>=0.1.0; extra == 'dev'
Provides-Extra: parquet
Requires-Dist: pyarrow>=14.0.0; extra == 'parquet'
